{"batchcomplete": "", "warnings": {"main": {"*": "Subscribe to the mediawiki-api-announce mailing list at <https://lists.wikimedia.org/postorius/lists/mediawiki-api-announce.lists.wikimedia.org/> for notice of API deprecations and breaking changes. Use [[Special:ApiFeatureUsage]] to see usage of deprecated features by your application."}, "revisions": {"*": "Because \"rvslots\" was not specified, a legacy format has been used for the output. This format is deprecated, and in the future the new format will always be used."}}, "query": {"normalized": [{"from": "Judas_Traveller", "to": "Judas Traveller"}], "pages": {"12435281": {"pageid": 12435281, "ns": 0, "title": "Judas Traveller", "revisions": [{"contentformat": "text/x-wiki", "contentmodel": "wikitext", "*": "#REDIRECT [[Clone Saga#The second Clone Saga]]\n\n{{Rcat shell|\n{{R to related topic}}\n}}"}]}}}}